inventree_digikey/__init__.py
inventree_digikey/digikey.py
inventree_digikey-0.0.1a0.dist-info/METADATA
inventree_digikey-0.0.1a0.dist-info/WHEEL
inventree_digikey-0.0.1a0.dist-info/entry_points.txt
inventree_digikey-0.0.1a0.dist-info/top_level.txt
inventree_digikey-0.0.1a0.dist-info/RECORD
