Metadata-Version: 2.1
Name: inventree-digikey
Version: 0.0.1a0
Summary: Digikey integration for InvenTree
Author-email: Matthias J Mair <info@mjmair.com>
License: MIT
Project-URL: repository, https://github.com/matmair/inventree-digikey
Project-URL: Bug Tracker, https://github.com/matmair/inventree-digikey/issues
Keywords: inventree,inventree-plugin,digikey
Classifier: Programming Language :: Python :: 3
Classifier: Operating System :: OS Independent
Classifier: Development Status :: 4 - Beta
Classifier: Environment :: Plugins
Classifier: Framework :: Django
Classifier: Intended Audience :: Developers
Classifier: Intended Audience :: Manufacturing
Classifier: Intended Audience :: End Users/Desktop
Classifier: Topic :: Scientific/Engineering
Requires-Python: >=3.6
Requires-Dist: requests
Requires-Dist: django
Provides-Extra: dev
Requires-Dist: twine ; extra == 'dev'
Requires-Dist: setuptools ; extra == 'dev'
